<?xml version="1.0" encoding="iso-2022-jp"?>
<givenPrograms xmlns="http://www.chorusroom.org/xml" xmlns:p="http://www.chorusroom.org/piece" xmlns:cr="http://www.chorusroom.org/character">
  <contestName>平成10年度(第65回)NHK全国学校音楽コンクール</contestName>
  <contestYear>1998</contestYear>
  <givenProgram>
    <givenProgramNumber>elementary-school</givenProgramNumber>
    <p:piece>
      <p:words-by>榎木冨士夫</p:words-by>
      <p:composed-by>寺島尚彦</p:composed-by>
      <p:title original="true" xml:lang="ja">
	<p:mainTitle>花と少女</p:mainTitle>
      </p:title>
    </p:piece>
    <!-- one of (p:piece p:suite) -->
  </givenProgram>
  <givenProgram>
    <givenProgramNumber>junior-highschool</givenProgramNumber>
    <p:piece>
      <p:words-by>蓬莱泰三</p:words-by>
      <p:composed-by>松下耕</p:composed-by>
      <p:title original="true" xml:lang="ja">
	<p:mainTitle>タンポポ</p:mainTitle>
      </p:title>
    </p:piece>
    <!-- one of (p:piece p:suite) -->
  </givenProgram>
  <givenProgram>
    <givenProgramNumber>senior-highschool</givenProgramNumber>
    <p:piece>
      <p:words-by>島田雅彦</p:words-by>
      <p:composed-by>三枝成彰</p:composed-by>
      <p:title original="true" xml:lang="ja">
	<p:mainTitle>また、あした</p:mainTitle>
      </p:title>
    </p:piece>
    <!-- one of (p:piece p:suite) -->
  </givenProgram>
</givenPrograms>
