<?xml version="1.0" encoding="utf-8"?><c:result moduleVersion="2.0"	xmlns:c="http://www.chorusroom.org/xml"	xmlns:p="http://www.chorusroom.org/piece"	xmlns="http://www.w3.org/1999/xhtml">  <c:competitionName>第71回NHK全国学校音楽コンクール奈良県大会</c:competitionName>  <c:date dayOfWeek="wed">2004-08-11</c:date>  <c:date dayOfWeek="thu">2004-08-12</c:date>  <c:hall>大和高田市文化会館さざんかホール</c:hall>  <c:referee job="声楽家･大阪音楽大学名誉教授">永井和子</c:referee>  <c:referee job="合唱指揮者･兵庫県合唱連盟副理事長">矢田正一</c:referee>  <c:referee job="合唱指揮者･奈良県合唱連盟理事長">池田光政</c:referee>  <c:referee job="奈良県教育委員会学校教育課指導主事">宮本憲二</c:referee>  <c:referee job="NHK奈良放送局放送部長">谷隆</c:referee>  <c:notice>    <p>各部門の課題曲は以下の通り。</p>    <ul>      <li>小学校の部…吉田美和作詞･作曲､寺島尚彦編曲:未来を旅するハーモニー</li>      <li>中学校の部…谷川俊太郎作詞､松下耕作曲:信じる</li>      <li>高等学校の部…大江健三郎作詞､信長貴富作曲:「新しい人」に</li>    </ul>  </c:notice>  <c:section>    <c:sectionName>小学校の部</c:sectionName>    <c:choir>      <c:name>下市町立阿知賀小学校</c:name>      <c:players>指揮:<c:conductor>上西秀勝</c:conductor>　ピアノ:<c:piano>熊谷啓子</c:piano></c:players>      <c:prize>金賞</c:prize>      <c:freeNumber><p:wordsBy>榎木冨士夫</p:wordsBy>作詞､<p:composedBy>寺島尚彦</p:composedBy>作曲：子供のための合唱組曲<p:suiteTitle>五つのスケッチ</p:suiteTitle>から<p:title>ねがい</p:title><p:title>変わりもの</p:title></c:freeNumber>    </c:choir>    <c:choir>      <c:name>大和高田市立高田小学校</c:name>      <c:players>指揮:<c:conductor>中嶋尚子</c:conductor>　ピアノ:<c:piano note="5年">岡本奈名</c:piano>、<c:piano>河合公子</c:piano></c:players>      <c:prize>銀賞</c:prize>      <c:freeNumber><p:wordsBy>山本嬰子</p:wordsBy>作詞、<p:composedBy>柳沢浩</p:composedBy>作曲：<p:title>七色の輪の中に</p:title></c:freeNumber>    </c:choir>    <c:choir>      <c:name>帝塚山小学校</c:name>      <c:players>指揮:<c:conductor>栗山葉子</c:conductor>　ピアノ:<c:piano>三栖智子</c:piano></c:players>      <c:prize>銀賞</c:prize>      <c:freeNumber><p:wordsBy>宮沢章二</p:wordsBy>作詞､<p:composedBy>橋本祥路</p:composedBy>作曲：同声合唱組曲<p:suiteTitle>いのち四章</p:suiteTitle>から<p:title>この海を</p:title></c:freeNumber>    </c:choir>    <c:choir>      <c:name>五條市立野原小学校</c:name>      <c:players>指揮:<c:conductor>仲谷富子</c:conductor>　ピアノ:<c:piano note="6年">角谷真美</c:piano>、<c:piano note="6年">長谷川真衣</c:piano></c:players>      <c:prize>銅賞</c:prize>      <c:freeNumber><p:wordsBy>東龍男</p:wordsBy>作詞､<p:composedBy>平吉毅州</p:composedBy>作曲：同声(女声)合唱組曲<p:suiteTitle>ぼくだけの歌</p:suiteTitle>から<p:title>ぼくのおうえんか</p:title></c:freeNumber>    </c:choir>    <c:choir>      <c:name>奈良市立富雄第三小学校</c:name>      <c:players>指揮:<c:conductor>山崎香世</c:conductor>　ピアノ:<c:piano>小杉舞</c:piano>、<c:piano>入部文香</c:piano></c:players>      <c:prize>銅賞</c:prize>      <c:freeNumber><p:wordsBy>中村千榮子</p:wordsBy>作詞､<p:composedBy>岩河三郎</p:composedBy>作曲：少年少女のための合唱組曲<p:suiteTitle>祭りと子ども</p:suiteTitle>から<p:title>秋祭り</p:title></c:freeNumber>    </c:choir>  </c:section>  <c:section>    <c:sectionName>中学校の部</c:sectionName>    <c:choir>      <c:name>広陵町立広陵中学校</c:name>      <c:type>女声</c:type>      <c:players>指揮:<c:conductor>足高モエ</c:conductor>　ピアノ:<c:piano>岩井里奈</c:piano></c:players>      <c:prize>金賞</c:prize>      <c:freeNumber><p:wordsBy>片岡輝</p:wordsBy>作詞､<p:composedBy>鈴木憲夫</p:composedBy>作曲：女声合唱組曲<p:suiteTitle>地球に寄り添って</p:suiteTitle>から<p:title>はばたく一本の葦〜小さなパスカル〜</p:title></c:freeNumber>    </c:choir>    <c:choir>      <c:name>下市町立下市中学校</c:name>      <c:type>女声</c:type>      <c:players>指揮:<c:conductor>大谷一仁</c:conductor>　ピアノ:<c:piano>大西康代</c:piano></c:players>      <c:prize>金賞</c:prize>      <c:freeNumber><p:wordsBy>G. アポリネール</p:wordsBy>作詞､<p:translatedBy>堀口大學</p:translatedBy>訳詞､<p:composedBy>高嶋みどり</p:composedBy>作曲：アポリネールの詩による四つの無伴奏小品集<p:suiteTitle>白鳥</p:suiteTitle>から<p:title>贈物</p:title></c:freeNumber>    </c:choir>    <c:choir>      <c:name>香芝市立香芝東中学校</c:name>      <c:type>女声</c:type>      <c:players>指揮:<c:conductor>向手江美</c:conductor>　ピアノ:<c:piano>瓜生祥子</c:piano></c:players>      <c:prize>銀賞</c:prize>      <c:freeNumber><p:wordsBy>谷川俊太郎</p:wordsBy>作詞､<p:composedBy>新実徳英</p:composedBy>作曲：女声合唱曲集<p:suiteTitle>空に､樹に…</p:suiteTitle>から<p:title>生きる</p:title></c:freeNumber>    </c:choir>    <c:choir>      <c:name>香芝市立香芝中学校</c:name>      <c:type>女声</c:type>      <c:players>指揮:<c:conductor>大畑佐知</c:conductor>　ピアノ:<c:piano>村井美伸</c:piano></c:players>      <c:prize>銀賞</c:prize>      <c:freeNumber><p:wordsBy>関根栄一</p:wordsBy>作詞､<p:composedBy>湯山昭</p:composedBy>作曲：女声合唱組曲<p:suiteTitle>鮎の歌</p:suiteTitle>から<p:title>鮎の歌</p:title></c:freeNumber>    </c:choir>    <c:choir>      <c:name>平群町立平群中学校</c:name>      <c:type>女声</c:type>      <c:players>指揮:<c:conductor>藪内京子</c:conductor>　ピアノ:<c:piano>西野智可子</c:piano></c:players>      <c:prize>銅賞</c:prize>      <c:freeNumber><p:wordsBy>御木白日</p:wordsBy>作詞､<p:composedBy>大熊崇子</p:composedBy>作曲：<p:title>さくら</p:title></c:freeNumber>    </c:choir>    <c:choir>      <c:name>三郷町立三郷中学校</c:name>      <c:type>女声</c:type>      <c:players>指揮:<c:conductor>河田早紀</c:conductor>　ピアノ:<c:piano>南由美</c:piano></c:players>      <c:prize>銅賞</c:prize>      <c:freeNumber><p:wordsBy>片岡輝</p:wordsBy>作詞､<p:composedBy>鈴木憲夫</p:composedBy>作曲：女声合唱組曲<p:suiteTitle>地球に寄り添って</p:suiteTitle>から<p:title>瞳の宇宙〜Cosmos in my eyes〜</p:title></c:freeNumber>    </c:choir>    <c:choir>      <c:name>香芝市立香芝北中学校</c:name>      <c:type>女声</c:type>      <c:players>指揮:<c:conductor>長濱文恵</c:conductor>　ピアノ:<c:piano>水野良美</c:piano>､<c:piano>畑野ナオミ</c:piano></c:players>      <c:prize>銅賞</c:prize>      <c:freeNumber><p:wordsBy>片岡輝</p:wordsBy>作詞､<p:composedBy>鈴木憲夫</p:composedBy>作曲：女声合唱組曲<p:suiteTitle>地球に寄り添って</p:suiteTitle>から<p:title>はばたく一本の葦〜小さなパスカル〜</p:title></c:freeNumber>    </c:choir>    <c:choir>      <c:name>奈良市立三笠中学校</c:name>      <c:type>女声</c:type>      <c:players>指揮:<c:conductor>浦恩城利明</c:conductor>　ピアノ:<c:piano>こしおなおみ</c:piano>､<c:piano note="3年">福井わか菜</c:piano></c:players>      <c:prize></c:prize>      <c:freeNumber><p:wordsBy>岩間芳樹</p:wordsBy>作詞､<p:composedBy>新実徳英</p:composedBy>作曲:女声合唱曲集<p:suiteTitle>空に､樹に…</p:suiteTitle>から<p:title>聞こえる</p:title></c:freeNumber>    </c:choir>    <c:choir>      <c:name>當麻町立白鳳中学校</c:name>      <c:type>女声</c:type>      <c:players>指揮:<c:conductor>奥田裕子</c:conductor>　ピアノ:<c:piano>西本温美</c:piano></c:players>      <c:prize></c:prize>      <c:freeNumber><p:wordsBy>片岡輝</p:wordsBy>作詞､<p:composedBy>鈴木憲夫</p:composedBy>作曲：女声合唱組曲<p:suiteTitle>地球に寄り添って</p:suiteTitle>から<p:title>はばたく一本の葦〜小さなパスカル〜</p:title></c:freeNumber>    </c:choir>    <c:choir>      <c:name>奈良市立伏見中学校･大和郡山市立片桐中学校合同</c:name>      <c:type>女声</c:type>      <c:players>指揮:<c:conductor>山中充子</c:conductor>　ピアノ:<c:piano>小林千賀子</c:piano></c:players>      <c:prize></c:prize>      <c:freeNumber><p:wordsBy>宮澤賢治</p:wordsBy>作詞､<p:composedBy>鈴木輝昭</p:composedBy>作曲：童声（女声）合唱とピアノのための<p:suiteTitle>イーハトーヴ組曲</p:suiteTitle>から<p:title>星めぐりの歌</p:title></c:freeNumber>    </c:choir>  </c:section>  <c:section>    <c:sectionName>高等学校の部</c:sectionName>    <c:choir>      <c:name>奈良県立高田高等学校</c:name>      <c:type>女声</c:type>      <c:players>指揮:<c:conductor>西田実子</c:conductor>　ピアノ:<c:piano>水尾晃子</c:piano></c:players>      <c:prize>金賞</c:prize>      <c:freeNumber><p:composedBy>福島雄次郎</p:composedBy>作曲:無伴奏女声合唱のための<p:suiteTitle>南島歌遊び&#x2161;</p:suiteTitle>その３映像から<p:title>酒､酒､酒</p:title></c:freeNumber>    </c:choir>    <c:choir>      <c:name>奈良県立生駒高等学校</c:name>      <c:type>混声</c:type>      <c:players>指揮:<c:conductor>下市紫津子</c:conductor>　ピアノ:<c:piano>津田麻祐子</c:piano></c:players>      <c:prize>銀賞</c:prize>      <c:freeNumber><p:wordsBy>谷川俊太郎</p:wordsBy>作詞､<p:composedBy>三善晃</p:composedBy>作曲:混声合唱のための<p:suiteTitle>地球へのバラード</p:suiteTitle>から<p:title>私が歌う理由</p:title></c:freeNumber>    </c:choir>    <c:choir>      <c:name>奈良県立橿原高等学校</c:name>      <c:type>女声</c:type>      <c:players>指揮:<c:conductor>勝蔦由佳</c:conductor>　ピアノ:<c:piano>勝蔦治美</c:piano></c:players>      <c:prize>銀賞</c:prize>      <c:freeNumber><p:composedBy>Miklós Kocsár</p:composedBy>作曲：<p:title>Salve Regina</p:title></c:freeNumber>    </c:choir>    <c:choir>      <c:name>奈良県立奈良高等学校</c:name>      <c:type>女声</c:type>      <c:players>指揮:<c:conductor>山白育枝</c:conductor>　ピアノ:<c:piano>山本有子</c:piano></c:players>      <c:prize>銅賞</c:prize>      <c:freeNumber><p:composedBy>J. Busto</p:composedBy>作曲:<p:title>Ave Maria gratia plena</p:title></c:freeNumber>      <c:freeNumber><p:composedBy>J. Busto</p:composedBy>作曲：<p:title>Alleluia</p:title></c:freeNumber>    </c:choir>  </c:section></c:result>