<?xml version="1.0" encoding="utf-8"?><c:result moduleVersion="2.0"	  xmlns:c="http://www.chorusroom.org/xml"	  xmlns:p="http://www.chorusroom.org/piece"	  xmlns="http://www.w3.org/1999/xhtml">  <c:competitionName>平成16年度(第71回)NHK全国学校音楽コンクール</c:competitionName>  <c:date dayOfWeek="fri">2004-08-27</c:date>  <c:hall>栗東芸術文化会館さきら大ホール</c:hall>  <c:referee job="合唱指揮者・滋賀県合唱連盟理事長">伊藤光子</c:referee>  <c:referee job="大阪信愛女学院短期大学教授">常野トシ子</c:referee>  <c:referee job="滋賀大学講師">中井憲照</c:referee>  <c:referee job="京都市立芸術大学講師">灘井誠</c:referee>  <c:referee job="NHK大津放送局副局長">山田隆</c:referee>  <c:section>    <c:sectionName>小学校の部</c:sectionName>    <c:choir>      <c:playingOrder>1</c:playingOrder>      <c:name>草津市立矢倉小学校</c:name>      <c:players>指揮：<c:conductor>竺悟温子</c:conductor>、ピアノ：<c:piano>梅村憲子</c:piano></c:players>      <c:prize>金賞</c:prize>      <c:special-prize>代表</c:special-prize>      <c:freeNumber><p:title>絵をかく夕日</p:title>（<p:wordsBy>宮田滋子</p:wordsBy>作詞、<p:composedBy>滝本泰三</p:composedBy>作曲）</c:freeNumber>    </c:choir>  </c:section>  <c:section>    <c:sectionName>中学校の部</c:sectionName>    <c:choir>      <c:playingOrder>1</c:playingOrder>      <c:name>日野町立日野中学校</c:name>      <c:type>混声</c:type>      <c:players>指揮：<c:conductor>遠城圭子</c:conductor>、ピアノ：<c:piano note="3年">中西麻菜</c:piano></c:players>      <c:prize>金賞</c:prize>      <c:special-prize>代表</c:special-prize>      <c:freeNumber>混声合唱組曲<p:suiteTitle>地球に寄り添って</p:suiteTitle>より<p:title>地球に寄り添って−センス　オブ　ワンダ−</p:title>（<p:wordsBy>片岡輝</p:wordsBy>作詞、<p:composedBy>鈴木憲夫</p:composedBy>作曲）</c:freeNumber>    </c:choir>    <c:choir>      <c:playingOrder>2</c:playingOrder>      <c:name>近江八幡市立八幡中学校</c:name>      <c:type>女声</c:type>      <c:players>指揮：<c:conductor>多賀準子</c:conductor>、ピアノ：<c:piano>山田千晶</c:piano></c:players>      <c:prize>銅賞</c:prize>      <c:freeNumber>女声合唱曲集<p:suiteTitle>地平線のかなたへ</p:suiteTitle>より<p:title>春に</p:title>（<p:wordsBy>谷川俊太郎</p:wordsBy>作詞、<p:composedBy>木下牧子</p:composedBy>作曲）</c:freeNumber>    </c:choir>    <c:choir>      <c:playingOrder>3</c:playingOrder>      <c:name>志賀町立志賀中学校</c:name>      <c:type>女声</c:type>      <c:players>指揮：<c:conductor>佐々木秀子</c:conductor>、ピアノ：<c:piano>三上恭子</c:piano></c:players>      <c:prize>銀賞</c:prize>      <c:freeNumber><p:title>星の生まれる夜</p:title>（<p:wordsBy>橋爪文</p:wordsBy>作詞、<p:composedBy>川崎祥悦</p:composedBy>作曲）</c:freeNumber>    </c:choir>  </c:section>  <c:section>    <c:sectionName>高等学校の部</c:sectionName>    <c:choir>      <c:playingOrder>1</c:playingOrder>      <c:name>滋賀県立膳所高等学校</c:name>      <c:type>女声</c:type>      <c:players>指揮：<c:conductor>福井浩</c:conductor>、ピアノ：<c:piano>直村かほる</c:piano></c:players>      <c:prize>金賞</c:prize>      <c:special-prize>代表</c:special-prize>      <c:freeNumber>無伴奏女声合唱のための<p:suiteTitle>南島歌遊び</p:suiteTitle>その１「版画」より<p:title>朝の祈り</p:title><p:title>収穫</p:title><p:title>陽気な娘たち</p:title> (<p:composedBy>福島雄次郎</p:composedBy>作曲)</c:freeNumber>    </c:choir>    <c:choir>      <c:playingOrder>2</c:playingOrder>      <c:name>滋賀県立八日市高等学校</c:name>      <c:type>混声</c:type>      <c:players>指揮：<c:conductor>藤村あさぎ</c:conductor>、ピアノ：<c:piano>塚本福美</c:piano></c:players>      <c:prize>銀賞</c:prize>      <c:freeNumber>混声合唱曲集<p:suiteTitle>光と風をつれて</p:suiteTitle>より<p:title>はじまり</p:title>（<p:wordsBy>工藤直子</p:wordsBy>作詞、<p:composedBy>木下牧子</p:composedBy>作曲）</c:freeNumber>    </c:choir>  </c:section></c:result>